MANIFEST.in
README.rst
setup.py
behind_lb/__init__.py
behind_lb/middleware.py
django_behind_lb.egg-info/PKG-INFO
django_behind_lb.egg-info/SOURCES.txt
django_behind_lb.egg-info/dependency_links.txt
django_behind_lb.egg-info/top_level.txt