Metadata-Version: 1.1
Name: django-behind-lb
Version: 0.1
Summary: A very efficient and simple Django middleware to obtain the real IP address from the headers sent by a trusted load balancer
Home-page: http://www.apsl.net/
Author: Ricardo Galli
Author-email: gallir@gmail.com
License: Public Domain
Platform: UNKNOWN
Classifier: Environment :: Web Environment
Classifier: Framework :: Django
Classifier: Intended Audience :: Developers
Classifier: License :: Public Domain
Classifier: Operating System :: OS Independent
Classifier: Programming Language :: Python
Classifier: Programming Language :: Python :: 3
Classifier: Programming Language :: Python :: 2
Classifier: Topic :: Internet :: WWW/HTTP
